{"sections":{"main":{"type":"template--cart","settings":{}},"rich-text":{"type":"text--rich-text","settings":{"colors":"light"}},"featured-collection":{"type":"collection--featured-collection","blocks":{"featured-collection-0":{"type":"grid-card-title","settings":{}},"featured-collection-1":{"type":"grid-card-price","settings":{}},"featured-collection-2":{"type":"grid-card-swatches","settings":{}}},"block_order":["featured-collection-0","featured-collection-1","featured-collection-2"],"settings":{"grid":3}}},"order":["main","rich-text","featured-collection"]}